{
  "name": "Lela Shelton",
  "age": 41,
  "address": {
    "street": "Cided Park",
    "city": "Andeze",
    "state": "AL",
    "zip": "67705"
  },
  "contact": {
    "phone": "(708) 603-2878",
    "servicePhone": "800889147"
  },
  "birthday": "1964-01-04T06:39:23.413Z",
  "ip": "190.19.6.197",
  "foo": "bar",
  "profile": {
    "about": "Dukcisih wibehfiv gewrak ot gib adojef zepetij cij loruvuda wu kad vikatse nawujat wonipu. Sumfe bu fo loninmo aba waici rak vuz lidag ji babuci zer vogahi lur gog mi vaz. Kecti hucotu efehu fe mugped naliodo va nodun muvcolfap dehu ta cainufug. Cawgosnub hob mos mafvavuj bebemoja dat zauveme de ni od nosdewon puom miruneh. Ba su gec dul mejpis jih baj dup bubilo bienror af rufve geze sempisi ijiwwag. Me arezijvi jur fapeg ma ja ru puh caaw ukuod uzu zeehe.",
    "bio": "Lifevu tuhapuz zamekiv sinpi lieb bi gikkam ijukicew zuvuf savtijapa pahapu ez usenjon cadal jo pego julam. Jajhanwa avtiwa gobdu ma fo riffeler opi pol jacuc rofas hahuf kiceig iti. Lurnoggu zuzgasete uc giutej gaweza ezzezaj honahzom puksurruw miki baod buepefu ekud vov ov sam jut. Baherog zatmuj gihjuve disuw fo bi si hufve welodopik fufehho sizgo ziz ojife bov mej sah cajig ded."
  },
  "apiKey": "ea3dbde29478a58e5d7dac027166198cc9025c65bafaf493031969c3146d888c",
  "currency": {
    "code": "GMD",
    "name": "Gambia Dalasi"
  }
}