{
  "name": "Peter Taylor",
  "age": 45,
  "address": {
    "street": "Ijbac Center",
    "city": "Cuzokvif",
    "state": "PA",
    "zip": "94339"
  },
  "contact": {
    "phone": "(511) 607-3278",
    "servicePhone": "800944123"
  },
  "birthday": "1962-09-24T04:33:40.952Z",
  "ip": "156.208.131.218",
  "foo": "bar",
  "profile": {
    "about": "Vic reb fume arezodi lobojed jaovhev ewepato ijekep devuru suhar rorcibkol bokowe lisi. Laju sic hijfad wum vah betna oguvep to beb begtin zag salvecuc putede ed lod ridsohca wahezna kaguhoga. Vu kib dufkurok budwid nukusi sonojman kodcukgu wizdotaj riaswah vohizbij pin zibaccot metse adreoja efez. Ticud saojidef vaprab bi dev bewemut gi ce rafo tozug ud vocigi meivu guidite jizlum ocatez jaduvku. Gusmaf enofecev fu zobusup dereen ojo homikur fadhujfi pa ted dafuz us ef gawuzoh at oce.",
    "bio": "Lacoc havlo hifahluv zam vu fa sajwinu askot luvpaveb fe vi kear joca cazag fakhevta ewe lif. Ipjudip vafsomnog giv sagoso uguceme ciuvci nah ta wuwle riekaha ezeunmi binpuszoj hunakja uk bebziwa degimac. Vok wusar aziza nislih um luka jobve puhnuic ohdu lofgej gatci wudmoko baen lozoezo raginnut."
  },
  "apiKey": "1eebad8ad08b79a926edc5dfb8a11c0eda7ffd3bff5503f017d912e15aadd914",
  "currency": {
    "code": "LKR",
    "name": "Sri Lanka Rupee"
  }
}