{
  "name": "Jeanette Meyer",
  "age": 61,
  "address": {
    "street": "Kajur Trail",
    "city": "Pifahubok",
    "state": "RI",
    "zip": "77035"
  },
  "contact": {
    "phone": "(460) 246-5650",
    "servicePhone": "800851184"
  },
  "birthday": "2001-04-30T10:17:14.950Z",
  "ip": "136.196.117.45",
  "foo": "bar",
  "profile": {
    "about": "Mo low mopo zo pac ma siwjec ahmeh oz reri vekpaile binofa oma guun vi til. Botawizaw icha onele ratdi zumdesu pe ici igokafcid cuvaceruj onhirvat kiziza muhe ane uhafuc. Dessev ode kis wagi jetuv oz ginivtu coshibe tito avoran berwika mavjorzec cekes ruuw eprit webluljo pin.",
    "bio": "Lafad wuj nol immef to kejusuw fi nutabji luli ot purocin wuhi. Tergiop tugil viltera tumac wa sir uc ducsal we hedeola duj ujbiti. Dodijel supum dejaw ukuka cisaj melup od sopkok zem tofuvwin lucizkeg arigac. Livuh nelravav jol be nadfut tu zorakhur co war wi adozi ceteb bive sumu. Wo vo orobufi cailce posruw alecom mocifi mafme puv ro gazsomzar fib icokar vuma kah ofu inaevope. Vihsivdu ogfed zacoti lef pev hafuzze wazhi koz benzi nevgaca megbo irzi. Sabamage raviwkiz mibeskaj desufsa webgepug jobfeduge ek ifinze ufukizo ezawim je ulsajsun doita."
  },
  "apiKey": "28c6b4dc0c5f81ea47aa9c8b27ccf5cea5056e5d30c5fa04a9d0dde2ad15d0fe",
  "currency": {
    "code": "BMD",
    "name": "Bermuda Dollar"
  }
}